diffscope/__init__.py
diffscope/models.py
diffscope/core/__init__.py
diffscope/core/commit_analyzer.py
diffscope/core/function_detector.py
diffscope/core/git_analyzer.py
diffscope/parsers/__init__.py
diffscope/parsers/function_parser.py
diffscope/parsers/tree_sitter_utils.py
diffscope/utils/__init__.py
diffscope/utils/diff_utils.py
diffscope/utils/github_api.py
diffscope/utils/logging.py
diffscope-0.2.1.dist-info/licenses/LICENSE
diffscope-0.2.1.dist-info/METADATA
diffscope-0.2.1.dist-info/WHEEL
diffscope-0.2.1.dist-info/entry_points.txt
diffscope-0.2.1.dist-info/top_level.txt
diffscope-0.2.1.dist-info/RECORD
