Metadata-Version: 2.4
Name: diffscope
Version: 0.2.1
Summary: Function-level git commit analysis tool
Home-page: https://github.com/yourusername/DiffScope
Author: DiffScope Team
Author-email: your.email@example.com
Project-URL: Bug Tracker, https://github.com/yourusername/DiffScope/issues
Project-URL: Documentation, https://github.com/yourusername/DiffScope/docs
Project-URL: Source Code, https://github.com/yourusername/DiffScope
Classifier: Development Status :: 4 - Beta
Classifier: Intended Audience :: Developers
Classifier: Topic :: Software Development :: Version Control :: Git
Classifier: Programming Language :: Python :: 3
Classifier: Programming Language :: Python :: 3.8
Classifier: Programming Language :: Python :: 3.9
Classifier: Programming Language :: Python :: 3.10
Classifier: License :: OSI Approved :: MIT License
Classifier: Operating System :: OS Independent
Requires-Python: >=3.8
License-File: LICENSE
Requires-Dist: requests>=2.25.0
Requires-Dist: PyGithub>=2.1.1
Requires-Dist: tree-sitter>=0.20.1
Requires-Dist: structlog>=23.1.0
Provides-Extra: dev
Requires-Dist: pytest>=7.0.0; extra == "dev"
Requires-Dist: pytest-cov>=4.0.0; extra == "dev"
Requires-Dist: black>=23.0.0; extra == "dev"
Requires-Dist: isort>=5.12.0; extra == "dev"
Requires-Dist: mypy>=1.0.0; extra == "dev"
Provides-Extra: docs
Requires-Dist: sphinx>=6.0.0; extra == "docs"
Requires-Dist: sphinx-rtd-theme>=1.2.0; extra == "docs"
Dynamic: author
Dynamic: author-email
Dynamic: classifier
Dynamic: description
Dynamic: description-content-type
Dynamic: home-page
Dynamic: license-file
Dynamic: project-url
Dynamic: provides-extra
Dynamic: requires-dist
Dynamic: requires-python
Dynamic: summary
